taskwarrior_scheduler/core.py
taskwarrior_scheduler/main.py
taskwarrior_scheduler/stats.py
taskwarrior_scheduler/timewarrior.py
taskwarrior_scheduler/utils.py
taskwarrior_scheduler-0.1.1.dist-info/METADATA
taskwarrior_scheduler-0.1.1.dist-info/WHEEL
taskwarrior_scheduler-0.1.1.dist-info/entry_points.txt
taskwarrior_scheduler-0.1.1.dist-info/licenses/LICENSE
taskwarrior_scheduler-0.1.1.dist-info/RECORD
