Metadata-Version: 2.4
Name: taskwarrior_scheduler
Version: 0.1.1
Summary: Indicates which taskwarrior's task should be done, considering time spent on other tasks
License: GPL-3.0-or-later
License-File: LICENSE
Author: Flávio Tapajós
Author-email: tapajos@outlook.com
Requires-Python: >=3.13
Classifier: License :: OSI Approved :: GNU General Public License v3 or later (GPLv3+)
Classifier: Programming Language :: Python :: 3
Classifier: Programming Language :: Python :: 3.13
Classifier: Programming Language :: Python :: 3.14
Requires-Dist: tasklib (>=2.5.1,<3.0.0)
Requires-Dist: typer (>=0.15.2,<0.16.0)
